Metadata-Version: 1.1
Name: gwtb-atom-generator
Version: 0.0.2
Summary: Gone with the Blastwave Atom feed generator.
Home-page: https://github.com/Bystroushaak/gwtb_atom_generator
Author: Bystroushaak
Author-email: bystrousak@kitakitsune.org
License: MIT
Download-URL: https://github.com/Bystroushaak/gwtb_atom_generator/tarball/0.0.2
Platform: UNKNOWN
Classifier: Development Status :: 3 - Alpha
Classifier: Intended Audience :: Developers
Classifier: Programming Language :: Python :: 3
